{
  "meta": {
    "version": 1,
    "updated_at": "2026-01-10",
    "notice_message": "설 연휴 운행 시간이 변경될 수 있습니다.",
    "contact_email": "help@localbus.com"
  },
  "holidays": [
    "2026-01-01",
    "2026-02-09",
    "2026-02-10",
    "2026-02-11",
    "2026-03-01",
    "2026-05-05",
    "2026-06-06",
    "2026-08-15",
    "2026-09-28",
    "2026-09-29",
    "2026-09-30",
    "2026-10-03",
    "2026-10-09",
    "2026-12-25"
  ],
  "timetable": {
    "weekday": [
      "06:00", "06:20", "06:40", "07:00", "07:20", "07:40",
      "08:00", "08:20", "08:40", "09:00", "09:20", "09:40",
      "10:00", "10:20", "10:40", "11:00", "11:20", "11:40",
      "12:00", "12:20", "12:40", "13:00", "13:20", "13:40",
      "14:00", "14:20", "14:40", "15:00", "15:20", "15:40",
      "16:00", "16:20", "16:40", "17:00", "17:20", "17:40",
      "18:00", "18:20", "18:40", "19:00", "19:20", "19:40",
      "20:00", "20:20", "20:40", "21:00", "21:20", "21:40"
    ],
    "weekend": [
      "07:00", "07:30", "08:00", "08:30", "09:00", "09:30",
      "10:00", "10:30", "11:00", "11:30", "12:00", "12:30",
      "13:00", "13:30", "14:00", "14:30", "15:00", "15:30",
      "16:00", "16:30", "17:00", "17:30", "18:00", "18:30",
      "19:00", "19:30", "20:00", "20:30", "21:00", "21:30"
    ]
  }
}
